[{"__type__":"cc.SpriteFrame","content":{"name":"pvp_own","texture":"fb1TRSs29BJ402kkXUgQY6","rect":[1,0,218,23],"offset":[0,0],"originalSize":[220,23]}},{"__type__":"cc.BitmapFont","_name":"pvp_own","spriteFrame":{"__uuid__":"2aWKCd3DVIprz2FSg8jvTx"},"fontSize":40,"_fntConfig":{"commonHeight":40,"fontSize":40,"atlasName":"pvp_own.png","fontDefDictionary":{"48":{"rect":{"x":100,"y":0,"width":20,"height":23},"xOffset":0,"yOffset":0,"xAdvance":20},"49":{"rect":{"x":0,"y":0,"width":20,"height":23},"xOffset":0,"yOffset":0,"xAdvance":20},"50":{"rect":{"x":40,"y":0,"width":20,"height":23},"xOffset":0,"yOffset":0,"xAdvance":20},"51":{"rect":{"x":60,"y":0,"width":20,"height":23},"xOffset":0,"yOffset":0,"xAdvance":20},"52":{"rect":{"x":80,"y":0,"width":20,"height":23},"xOffset":0,"yOffset":0,"xAdvance":20},"53":{"rect":{"x":20,"y":0,"width":20,"height":23},"xOffset":0,"yOffset":0,"xAdvance":20},"54":{"rect":{"x":120,"y":0,"width":20,"height":23},"xOffset":0,"yOffset":0,"xAdvance":20},"55":{"rect":{"x":140,"y":0,"width":20,"height":23},"xOffset":0,"yOffset":0,"xAdvance":20},"56":{"rect":{"x":160,"y":0,"width":20,"height":23},"xOffset":0,"yOffset":0,"xAdvance":20},"57":{"rect":{"x":180,"y":0,"width":20,"height":23},"xOffset":0,"yOffset":0,"xAdvance":20},"120":{"rect":{"x":200,"y":0,"width":20,"height":23},"xOffset":0,"yOffset":0,"xAdvance":20}},"kerningDict":{}}}]